transcript_transformer/__init__.py
transcript_transformer/argparser.py
transcript_transformer/data.py
transcript_transformer/models.py
transcript_transformer/processing.py
transcript_transformer/ribotie.py
transcript_transformer/tis_transformer.py
transcript_transformer/transcript_loader.py
transcript_transformer/transcript_transformer.py
transcript_transformer/util_functions.py
transcript_transformer/configs/__init__.py
transcript_transformer/configs/defaults.rt.yml
transcript_transformer/configs/defaults.tt.yml
transcript_transformer/pretrained/__init__.py
transcript_transformer/pretrained/rt_models/50perc_06_23.rt.yml
transcript_transformer/pretrained/rt_models/50perc_06_23_f0.rt.ckpt
transcript_transformer/pretrained/rt_models/50perc_06_23_f1.rt.ckpt
transcript_transformer/pretrained/rt_models/__init__.py
transcript_transformer/pretrained/tt_models/Homo_sapiens.GRCh38.113_f0.tt.ckpt
transcript_transformer/pretrained/tt_models/Homo_sapiens.GRCh38.113_f1.tt.ckpt
transcript_transformer/pretrained/tt_models/Homo_sapiens.GRCh38.113_f2.tt.ckpt
transcript_transformer/pretrained/tt_models/Homo_sapiens.GRCh38.113_f3.tt.ckpt
transcript_transformer/pretrained/tt_models/Homo_sapiens.GRCh38.113_f4.tt.ckpt
transcript_transformer/pretrained/tt_models/Homo_sapiens.GRCh38.113_params.tt.yml
transcript_transformer/pretrained/tt_models/Mus_musculus.GRCm39.112_f0.tt.ckpt
transcript_transformer/pretrained/tt_models/Mus_musculus.GRCm39.112_f1.tt.ckpt
transcript_transformer/pretrained/tt_models/Mus_musculus.GRCm39.112_f2.tt.ckpt
transcript_transformer/pretrained/tt_models/Mus_musculus.GRCm39.112_f3.tt.ckpt
transcript_transformer/pretrained/tt_models/Mus_musculus.GRCm39.112_f4.tt.ckpt
transcript_transformer/pretrained/tt_models/Mus_musculus.GRCm39.112_params.tt.yml
transcript_transformer/pretrained/tt_models/__init__.py
transcript_transformer-1.0.1.dist-info/licenses/LICENCE
transcript_transformer-1.0.1.dist-info/METADATA
transcript_transformer-1.0.1.dist-info/WHEEL
transcript_transformer-1.0.1.dist-info/entry_points.txt
transcript_transformer-1.0.1.dist-info/top_level.txt
transcript_transformer-1.0.1.dist-info/RECORD
