Metadata-Version: 2.4
Name: transcript-transformer
Version: 1.0.1
Summary: Transformers for Transcripts
Author: Jim Clauwaert
Project-URL: Homepage, https://github.com/TRISTAN-ORF/TRISTAN
Project-URL: Bug Tracker, https://github.com/TRISTAN-ORF/TRISTAN/issues
Keywords: transformer,transcript,bioinformatics,ORF
Classifier: Programming Language :: Python :: 3
Classifier: Programming Language :: Python :: 3.10
Classifier: Programming Language :: Python :: 3.11
Classifier: License :: OSI Approved :: MIT License
Classifier: Operating System :: OS Independent
Classifier: Topic :: Scientific/Engineering :: Bio-Informatics
Requires-Python: >=3.10
License-File: LICENCE
Requires-Dist: pytorch-lightning>=2.2.1
Requires-Dist: tensorboard>=2.16.2
Requires-Dist: torchmetrics>=1.1.2
Requires-Dist: performer-pytorch==1.1.4
Requires-Dist: local-attention==1.7.1
Requires-Dist: h5py>=3.11.0
Requires-Dist: numpy>=1.26.4
Requires-Dist: scipy>=1.13.0
Requires-Dist: pandas>=2.2.2
Requires-Dist: biobear>=0.23.7
Requires-Dist: pyarrow>=18.0.0
Requires-Dist: h5max==0.3.2
Requires-Dist: fasta-reader==3.0.2
Requires-Dist: polars==1.28
Requires-Dist: tqdm>=4.66.2
Requires-Dist: pyfaidx==0.8.1.1
Requires-Dist: gtfparse-transcript-transformer==2.5.0
Dynamic: license-file
